nsf_logging/__init__.py
nsf_utils-0.0.1.dist-info/LICENSE
nsf_utils-0.0.1.dist-info/METADATA
nsf_utils-0.0.1.dist-info/WHEEL
nsf_utils-0.0.1.dist-info/top_level.txt
nsf_utils-0.0.1.dist-info/RECORD
